pyisa/__init__.py
pyisa/build.py
pyisa-1.0.dist-info/METADATA
pyisa-1.0.dist-info/RECORD
pyisa-1.0.dist-info/WHEEL
pyisa-1.0.dist-info/top_level.txt
