Metadata-Version: 2.1
Name: pyisa
Version: 1.0
Summary: Basic project structure creation for Data Science Projects
Home-page: https://github.com/sagard21/pyisa
Author: Sagar Dawda
Author-email: sagard21@gmail.com
License: MIT License
Platform: UNKNOWN
Classifier: Programming Language :: Python :: 2.7
Classifier: Operating System :: OS Independent
